cmocean/__init__.py
cmocean/cm.py
cmocean/data.py
cmocean/plots.py
cmocean/tools.py
cmocean/rgb/algae-rgb.txt
cmocean/rgb/amp-rgb.txt
cmocean/rgb/balance-rgb.txt
cmocean/rgb/curl-rgb.txt
cmocean/rgb/deep-rgb.txt
cmocean/rgb/delta-rgb.txt
cmocean/rgb/dense-rgb.txt
cmocean/rgb/diff-rgb.txt
cmocean/rgb/gray-rgb.txt
cmocean/rgb/haline-rgb.txt
cmocean/rgb/ice-rgb.txt
cmocean/rgb/matter-rgb.txt
cmocean/rgb/oxy-rgb.txt
cmocean/rgb/phase-rgb.txt
cmocean/rgb/rain-rgb.txt
cmocean/rgb/solar-rgb.txt
cmocean/rgb/speed-rgb.txt
cmocean/rgb/tarn-rgb.txt
cmocean/rgb/tempo-rgb.txt
cmocean/rgb/thermal-rgb.txt
cmocean/rgb/topo-rgb.txt
cmocean/rgb/turbid-rgb.txt
cmocean/rgb/inverted/algae_i-rgb.txt
cmocean/rgb/inverted/amp_i-rgb.txt
cmocean/rgb/inverted/balance_i-rgb.txt
cmocean/rgb/inverted/curl_i-rgb.txt
cmocean/rgb/inverted/deep_i-rgb.txt
cmocean/rgb/inverted/delta_i-rgb.txt
cmocean/rgb/inverted/dense_i-rgb.txt
cmocean/rgb/inverted/diff_i-rgb.txt
cmocean/rgb/inverted/gray_i-rgb.txt
cmocean/rgb/inverted/haline_i-rgb.txt
cmocean/rgb/inverted/ice_i-rgb.txt
cmocean/rgb/inverted/matter_i-rgb.txt
cmocean/rgb/inverted/oxy_i-rgb.txt
cmocean/rgb/inverted/phase_i-rgb.txt
cmocean/rgb/inverted/rain_i-rgb.txt
cmocean/rgb/inverted/solar_i-rgb.txt
cmocean/rgb/inverted/speed_i-rgb.txt
cmocean/rgb/inverted/tarn_i-rgb.txt
cmocean/rgb/inverted/tempo_i-rgb.txt
cmocean/rgb/inverted/thermal_i-rgb.txt
cmocean/rgb/inverted/topo_i-rgb.txt
cmocean/rgb/inverted/turbid_i-rgb.txt
cmocean-4.0.3.dist-info/LICENSE.txt
cmocean-4.0.3.dist-info/METADATA
cmocean-4.0.3.dist-info/WHEEL
cmocean-4.0.3.dist-info/top_level.txt
cmocean-4.0.3.dist-info/RECORD
