Metadata-Version: 2.1
Name: cmocean
Version: 4.0.3
Summary: Colormaps for Oceanography
Home-page: https://github.com/matplotlib/cmocean
Author: Kristen Thyng
Author-email: kthyng@gmail.com
Keywords: colormaps,oceanography,plotting,visualization
Classifier: Development Status :: 3 - Alpha
Requires-Python: >=3.8
License-File: LICENSE.txt
Requires-Dist: matplotlib
Requires-Dist: numpy
Requires-Dist: packaging
Provides-Extra: plots
Requires-Dist: colorspacious; extra == "plots"
Requires-Dist: viscm; extra == "plots"
